{
  "Impossible d’envoyer l’email de test": "Unable to send test email",
  "Impossible de récupérer les métriques email": "Unable to retrieve email metrics",
  "Impossible de renvoyer l’email": "Unable to resend email",
  "Créations": "Creations",
  "Déplier le menu": "Expand menu",
  "Expéditions": "Expeditions",
  "Ingrédients": "Ingredients",
  "Paramètres boutique": "Store Settings",
  "Plier le menu": "Fold menu",
  "Réductions": "Discounts",
  "Se déconnecter": "Log out",
  "Aucun job automatique configuré.": "No automatic jobs configured.",
  "Configuration du job mise à jour": "Updated job configuration",
  "Dernière exécution": "Last execution",
  "Enregistrer la fréquence": "Save frequency",
  "Exécution impossible": "Unable to execute",
  "Fréquence (min)": "Frequency (min)",
  "Fréquence du job mise à jour": "Updated job frequency",
  "Impossible de charger les jobs automatiques": "Unable to load automatic jobs",
  "Job exécuté": "Job executed",
  "La fréquence doit être un nombre positif (minutes)": "Frequency must be a positive number (minutes)",
  "Lancer le job": "Start the job",
  "Mise à jour impossible": "Unable to update",
  "Prochaine exécution": "Next execution",
  "Surveillance et paramétrage des tâches backend": "Monitoring and configuring backend tasks",
  "Ajoutez au moins un ingrédient au blend.": "Add at least one ingredient to the blend.",
  "Annuler la modification": "Undo change",
  "Aucune création disponible.": "No creations available.",
  "Commande": "Order",
  "Créations (Blend Listings)": "Creations (Blend Listings)",
  "Créé par (createdBy)": "Created by (createdBy)",
  "Créez et éditez vos blends manuellement, puis publiez-les via les listings.": "Create and edit your blends manually, then publish them via listings.",
  "Description courte de la création": "Short description of the creation",
  "Exporter les blends": "Export blends",
  "Fichier sélectionné:": "Selected file:",
  "Importer le CSV": "Import CSV",
  "Impossible d'enregistrer cette création.": "Unable to save this creation.",
  "Impossible de créer ce création/listing.": "Unable to create this creation/listing.",
  "Impossible de supprimer cette création.": "Unable to delete this creation.",
  "Identifiants d'ingrédients": "Ingredient identifiers",
  "ingrédient(s)": "ingredients)",
  "Le fichier CSV est vide.": "The CSV file is empty.",
  "Le nom du blend est obligatoire.": "The name of the blend is mandatory.",
  "Le template et l'import utilisent les mêmes colonnes.": "The template and the import use the same columns.",
  "Le titre de la création est obligatoire.": "The title of the creation is required.",
  "Modifier": "To modify",
  "Modifier création/listing": "Edit creation/listing",
  "Nouveau création/listing": "New creation/listing",
  "Commande source (createdFromOrderId)": "Source order (createdFromOrderId)",
  "ou": "Or",
  "Sélectionnez un fichier CSV.": "Select a CSV file.",
  "Supprimer": "DELETE",
  "Télécharger modèle CSV": "Download CSV template",
  "Compte": "Account",
  "Dernière maj.": "Last update",
  "Email": "E-mail",
  "Invité": "Guest",
  "Suivi des paniers clients": "Tracking customer baskets",
  "Total (estimé)": "Total (estimated)",
  "Aucune adresse enregistrée.": "No address registered.",
  "Créé le": "Created on",
  "Date de naissance": "Date of birth",
  "Impossible de charger le client.": "Failed to load client.",
  "Livraison par défaut": "Default delivery",
  "Retour aux clients": "Return to customers",
  "Toutes les informations personnelles et adresses": "All personal information and addresses",
  "Type de compte": "Account type",
  "Afficher les filtres": "Show filters",
  "Aucun client trouvé.": "No customers found.",
  "Cette action est irréversible et supprimera en cascade ses paniers, commandes, créations, wishlists, adresses, sessions et données liées.": "This action is irreversible and will delete baskets, orders, creations, wishlists, addresses, sessions and linked data in cascade.",
  "Comptes (hors invités)": "Accounts (excluding guests)",
  "Date de création : du": "Date of creation: from",
  "Êtes-vous sûr de vouloir supprimer": "Are you sure you want to delete",
  "Gérez les comptes clients": "Manage customer accounts",
  "Impossible de supprimer ce client.": "Unable to delete this client.",
  "Invités uniquement": "Guests only",
  "Masquer les filtres": "Hide filters",
  "Supprimer définitivement": "Permanently delete",
  "Supprimer le client": "Delete customer",
  "Tous les types": "All types",
  "Aucune wishlist pour ce client.": "No wishlist for this customer.",
  "création": "creation",
  "Impossible de charger les wishlists du client.": "Unable to load customer wishlists.",
  "Liste des wishlists": "List of wishlists",
  "Ma création": "My creation",
  "Retour au dossier client": "Return to customer file",
  "| email échec/relance:": "| failure/retry email:",
  "À traiter": "To be treated",
  "Activité des 7 derniers jours": "Activity of the last 7 days",
  "Alertes opérationnelles": "Operational alerts",
  "Annulée": "Canceled",
  "Aucune catégorie": "No category",
  "Aucune commande pour le moment.": "No orders at the moment.",
  "CA du mois": "Turnover of the month",
  "Confirmée": "Confirmed",
  "Dernière actualisation:": "Last update:",
  "Dernières commandes": "Latest orders",
  "Emails en échec": "Failed emails",
  "Emails en file de retry": "Emails in retry queue",
  "En préparation": "In preparation",
  "Expédiée": "Shipped",
  "expéditions": "expeditions",
  "Expéditions en transit": "In-transit shipments",
  "Expéditions sans numéro de suivi": "Shipments without tracking number",
  "Graphique à barres des commandes sur les 7 derniers jours": "Bar chart of orders over the last 7 days",
  "ingrédients": "ingredients",
  "Ingrédients actifs": "Active ingredients",
  "Livrée": "Livery",
  "Panier moyen": "Average basket",
  "Préparations sans étiquette Boxtal": "Boxtal unlabeled preparations",
  "Priorités du jour": "Priorities of the day",
  "Remboursée": "Refunded",
  "sans suivi": "without tracking",
  "Santé des automatisations": "Automation health",
  "sur commandes payées": "on paid orders",
  "Tableau de bord": "Dashboard",
  "Voir les commandes": "View orders",
  "Voir les emails": "View emails",
  "Voir les expéditions": "View shipments",
  "Voir les jobs": "View jobs",
  "Vue pilotage: commandes, expéditions, communication client et points de blocage.": "Management view: orders, shipments, customer communication and blocking points.",
  "Activer les limites": "Enable limits",
  "Autoriser la combinaison avec d’autres réductions": "Allow combination with other discounts",
  "Configuration JSON requise pour ce type": "JSON configuration required for this type",
  "Configurez les règles de réduction.": "Configure discount rules.",
  "Impossible d'enregistrer la réduction": "Unable to save discount",
  "Impossible de charger la réduction": "Unable to load discount",
  "La configuration doit être un objet JSON": "Configuration must be a JSON object",
  "Livraison gratuite": "Free delivery",
  "Modifier la réduction": "Edit discount",
  "Nouvelle réduction": "New reduction",
  "Période de validité": "Validity period",
  "Première commande uniquement": "First order only",
  "Retour": "Back",
  "BOGO / 1 acheté = 1 offert": "BOGO / 1 purchased = 1 free",
  "Code / Méthode": "Code/Method",
  "Désactiver": "Disable",
  "Échec de la mise à jour": "Update failed",
  "Gérez les promotions et codes de réduction.": "Manage promotions and discount codes.",
  "Impossible de charger les réductions": "Unable to load discounts",
  "Période": "Period",
  "Prix barré (prix promotionnel)": "Crossed out price (promotional price)",
  "Aucun email trouvé": "No emails found",
  "Échec de l'envoi test": "Test send failed",
  "Email de test envoyé": "Test email sent",
  "Email de test envoyé depuis le back-office.": "Test email sent from the back office.",
  "Email de relance envoyé avec succès": "Follow-up email sent successfully",
  "Relance impossible": "Relaunch impossible",
  "Historique, relance et KPI des emails transactionnels et marketing": "History, follow-up and KPIs of transactional and marketing emails",
  "Impossible de charger les emails": "Unable to load emails",
  "Précédent": "Previous",
  "Renseigne un email de test": "Enter a test email",
  "Test email My Own Tea": "My Own Tea email test",
  "Tous les statuts": "All statuses",
  "0 résultat": "0 results",
  "1 - disparaît vite": "1 - disappears quickly",
  "1 - léger, fluide": "1 - light, fluid",
  "1 - très doux": "1 - very soft",
  "2 - léger, un peu rond": "2 - light, a little round",
  "2 - légère rondeur": "2 - slight roundness",
  "2 - légèrement doux": "2 - slightly sweet",
  "3 - douceur modérée": "3 - moderate sweetness",
  "3 - net, équilibré": "3 - clean, balanced",
  "3 - présent, harmonieux": "3 - present, harmonious",
  "4 - dense, velouté": "4 - dense, velvety",
  "4 - marqué, très rond": "4 - marked, very round",
  "4 - puissant, bien marqué": "4 - powerful, well marked",
  "5 - très dense, sirupeux": "5 - very dense, syrupy",
  "5 - très doux, gourmand": "5 - very sweet, delicious",
  "5 - très longue, évolutive": "5 - very long, scalable",
  "5 - très présent, enveloppant": "5 - very present, enveloping",
  "5 - très puissant, marqué": "5 - very powerful, marked",
  "Acidulé": "Acidulous",
  "Afficher les colonnes": "Show columns",
  "Affini-thé": "Affini-tea",
  "Ajouter": "Add",
  "Ajouter un ingrédient": "Add an ingredient",
  "Amère": "Bitter",
  "Anisé": "Aniseed",
  "Après-midi": "Afternoon",
  "Arômes Naturels": "Natural Flavors",
  "Aucun ingrédient trouvé.": "No ingredients found.",
  "Bienfaits (sélection multiple)": "Benefits (multiple selection)",
  "Bon pour la circulation sanguine": "Good for blood circulation",
  "Catégorie": "Category",
  "Catégorie *": "Category *",
  "Citronné": "Lemony",
  "Délicat": "Delicate",
  "Diurétique léger": "Mild diuretic",
  "Énergie": "Energy",
  "Épaisseur (1-5)": "Thickness (1-5)",
  "Épicé": "Spicy",
  "Format non supporte. Utilisez JPG, PNG, WebP ou GIF.": "Format not supported. Use JPG, PNG, WebP or GIF.",
  "Fruité": "Fruity",
  "Herbacé": "Herbaceous",
  "Immunité": "Immunity",
  "Impossible d’enregistrer l’ingrédient": "Unable to save ingredient",
  "Impossible de supprimer l’ingrédient": "Unable to delete ingredient",
  "Intensité (1-5)": "Intensity (1-5)",
  "Léger": "Light",
  "Légèrement Acide": "Slightly Acidic",
  "Légèrement Amère": "Slightly Bitter",
  "Légèrement Épicé": "Slightly Spicy",
  "Maintenez Ctrl (ou Cmd) pour sélectionner plusieurs options": "Hold Ctrl (or Cmd) to select multiple options",
  "Masquer les colonnes": "Hide columns",
  "Mentholé": "Minty",
  "Modifié le": "Modified on",
  "Moment de la journée": "Time of day",
  "Préparation": "Preparation",
  "Profil arômatique": "Flavor profile",
  "Rafraîchissant": "Refreshing",
  "Rechercher un ingrédient...": "Search for an ingredient...",
  "Réinitialiser": "Reset",
  "Santé de la peau": "Skin health",
  "Santé des yeux": "Eye health",
  "Saveurs (sélection multiple)": "Flavors (multiple selection)",
  "Source d'Oméga-3": "Source of Omega-3",
  "Source de fer": "Source of iron",
  "Source de fibres": "Source of fiber",
  "Source de vitamine C": "Source of vitamin C",
  "Soutien de la tension artérielle": "Blood Pressure Support",
  "Sucré": "Sugar",
  "Sucrosité (1-5)": "Sweetness (1-5)",
  "Supprimer l'ingrédient": "Remove ingredient",
  "Température": "Temperature",
  "Texte long, visible sur la fiche ingrédient publique.": "Long text, visible on the public ingredient sheet.",
  "Toute intensité": "Any intensity",
  "Toute la journée": "All day",
  "Toutes catégories": "All categories",
  "un ingrédient": "an ingredient",
  "Upload impossible. Réessayez ou changez de fichier.": "Unable to upload. Try again or change files.",
  "URL de l'image": "Image URL",
  "Végétal": "Vegetal",
  "Créér une option": "Create an option",
  "Gérez les options et valeurs des produits": "Manage product options and values",
  "Supprimer cette option ?": "Remove this option?",
  "Supprimer cette valeur ?": "Delete this value?",
  "Détails de la commande": "Order details",
  "Impossible de charger la commande": "Unable to load order",
  "Livraison": "Delivery",
  "Paiement:": "Payment:",
  "Lien suivi": "Followed link",
  "réduction": "reduction",
  "réductions appliquées": "discounts applied",
  "Mise à jour du statut impossible": "Unable to update status",
  "No Commande": "Order No.",
  "Paiement": "Payment",
  "Statut commande mis à jour": "Order status updated",
  "Suivi et gestion des commandes clients": "Monitoring and management of customer orders",
  "Ajouter au pack": "Add to pack",
  "Aucun composant pour ce pack. Ajoutez une variante depuis le formulaire ci-dessus.": "No components for this pack. Add a variation from the form above.",
  "Composants du pack": "Pack components",
  "Composez vos packs avec précision en définissant les variantes et quantités incluses.": "Compose your packs precisely by defining the variants and quantities included.",
  "Pack sélectionné": "Selected pack",
  "Quantité": "Quantity",
  "Sélectionnez un pack": "Select a pack",
  "Sélectionnez un pack, puis ajoutez les variantes à inclure dans son contenu.": "Select a pack, then add variations to include in its content.",
  "Sélectionnez un produit": "Select a product",
  "Sélectionnez une variante": "Select a variant",
  "Supprimer cet élément ?": "Delete this item?",
  "Unités totales": "Total units",
  "Ajouter une option": "Add an option",
  "Ajouter une variante": "Add a variation",
  "Ajoutez des options/valeurs pour créer des variantes.": "Add options/values ​​to create variations.",
  "Certaines options n'ont pas encore de valeurs :": "Some options do not yet have values:",
  "Combinaisons incomplètes :": "Incomplete combinations:",
  "Créer": "Create",
  "Gestion des options et variantes": "Management of options and variants",
  "Le prix est requis.": "Price is required.",
  "Le titre et le slug sont requis.": "Title and slug are required.",
  "Mettre à jour": "To update",
  "Modifier le produit": "Edit product",
  "Retour à la liste": "Back to list",
  "Sélectionnez une valeur par option.": "Select one value per option.",
  "Supprimer cette variante ?": "Remove this variant?",
  "variantes créées.": "variants created.",
  "Ajouter un produit": "Add a product",
  "Gérez les produits et leur contenu": "Manage products and their content",
  "Liste des produits": "Product List",
  "Supprimer ce produit ?": "Remove this product?",
  "Aucune redirection trouvée": "No redirects found",
  "Aucune règle configurée.": "No rules configured.",
  "Chemin à tester requis": "Path to test required",
  "Début (optionnel)": "Start (optional)",
  "Dernière MAJ": "Last update",
  "Fenêtre:": "Window:",
  "Impossible de charger les règles": "Unable to load rules",
  "Locales ciblées (CSV)": "Targeted premises (CSV)",
  "Modifier une règle": "Edit a rule",
  "Nouvelle règle": "New rule",
  "Paramétrage des redirections": "Setting up redirects",
  "Pays ciblés (CSV)": "Targeted countries (CSV)",
  "Priorité": "Priority",
  "Priorité faible = priorité plus forte.": "Low priority = higher priority.",
  "Redirection promo été": "Summer promo redirection",
  "Règle active": "Active rule",
  "Règle créée": "Rule created",
  "Enregistrement impossible": "Unable to record",
  "Suppression impossible": "Unable to delete",
  "Test impossible": "Unable to test",
  "Règle mise à jour": "Updated rule",
  "Règle supprimée": "Rule removed",
  "Règles existantes": "Existing rules",
  "SEO, campagnes, maintenance, A/B test et règles pays/locale": "SEO, campaigns, maintenance, A/B testing and country/local rules",
  "Supprimer cette règle de redirection ?": "Remove this redirect rule?",
  "Test de résolution": "Resolution test",
  "Tester la règle appliquée": "Test the applied rule",
  "Type de matching": "Matching type",
  "à domicile,": "at home,",
  "Aperçu": "Preview",
  "Ces valeurs alimentent le front et le backend. Plus aucun montant n&apos;est codé en dur au checkout.": "These values ​​feed the front and backend. No amount is hardcoded at checkout anymore.",
  "en France.": "In France.",
  "en point relais. Livraison offerte dès": "at a relay point. Free delivery from",
  "Europe et DOM-TOM (centimes)": "Europe and DOM-TOM (cents)",
  "Frais par défaut (centimes)": "Default Fee (cents)",
  "France domicile": "France home",
  "France métropolitaine domicile (centimes)": "Metropolitan France home (cents)",
  "France métropolitaine point relais (centimes)": "Metropolitan France relay point (cents)",
  "France point relais": "France relay point",
  "France:": "France:",
  "Pilotez les règles de livraison globales utilisées au checkout.": "Manage the global delivery rules used at checkout.",
  "Réglages livraison": "Delivery settings",
  "Seuil livraison offerte (FR)": "Free delivery threshold (FR)",
  "Seuil livraison offerte France (centimes)": "Threshold free delivery France (cents)",
  "Valeur de repli backend:": "Backend fallback value:",
  "Aucune expédition pour le moment.": "No shipping at this time.",
  "cette expédition": "this expedition",
  "Étiquette": "Label",
  "Gestion des envois et étiquettes Boxtal": "Management of Boxtal shipments and labels",
  "Impossible de charger les expéditions": "Unable to load shipments",
  "Rafraîchir l'étiquette": "Refresh label",
  "Rafraîchir le suivi": "Refresh tracking",
  "Télécharger": "Download",
  "année": "year",
  "Aucun plan configuré pour le moment.": "No plans configured yet.",
  "Créer le plan": "Create the plan",
  "Créer un plan": "Create a plan",
  "Définissez l’intervalle de facturation et associez le Stripe Price ID correspondant.": "Set the billing interval and associate the corresponding Stripe Price ID.",
  "Mettez à jour les plans en place et gérez leur activation.": "Update existing plans and manage their activation.",
  "Plans configurés": "Configured plans",
  "Produits liés": "Related Products",
  "Reliez vos produits abonnables à Stripe pour activer un parcours récurrent clair et fiable.": "Connect your subscriberable products to Stripe to enable a clear and reliable recurring journey.",
  "Supprimer ce plan ?": "Delete this plan?",
  "Tous les (nombre)": "All (number)",
  "Créér": "Create",
  "Gérez les variantes de produits": "Manage product variants",
  "Modifier la variante": "Change variant",
  "Ajouter au panier": "Add to cart",
  "Voir détails": "See details",
  "Voir le détail": "See details",
  "Déconnexion": "Disconnect",
  "Mes adresses": "My addresses",
  "Mes commandes": "My orders",
  "Mes informations": "My information",
  "Adresse *": "Address *",
  "Adresse requise": "Address required",
  "Belgique": "Belgium",
  "Civilité *": "Civility *",
  "Complément / entreprise": "Supplement / business",
  "France": "France",
  "Macedoine du Nord": "North Macedonia",
  "Numéro de voie et voirie": "Lane number and roads",
  "Prénom *": "First name *",
  "Prénom requis": "First name required",
  "Téléphone portable *": "Cell phone *",
  "Utiliser comme adresse de facturation par défaut": "Use as default billing address",
  "Utiliser comme adresse de livraison par défaut": "Use as default shipping address",
  "État": "State",
  "Félicitations, vous bénéficiez de la livraison offerte !": "Congratulations, you benefit from free delivery!",
  "Livraison offerte dès 45 € d'achat": "Free delivery from 45 € of purchase",
  "Votre panier": "Your basket",
  "Aucun accessoire disponible pour le moment": "No accessories available at the moment",
  "Chargement des accessoires...": "Loading accessories...",
  "Des accessoires uniques pour accompagner votre dégustation": "Unique accessories to accompany your tasting",
  "Créer un nouveau mélange": "Create a new mixture",
  "Finaliser ma commande": "Finalize my order",
  "Augmenter la quantité": "Increase the quantity",
  "Diminuer la quantité": "Reduce the quantity",
  "Votre panier est vide.": "Your basket is empty.",
  "Sélectionnez vos ingrédients pour commencer": "Select your ingredients to get started",
  "Choisissez votre langue et votre pays": "Choose your language and country",
  "Français (Belgique)": "French (Belgium)",
  "Français (France)": "French (France)",
  "Nous utiliserons ce choix pour personnaliser votre expérience. Vous pourrez le modifier plus tard.": "We will use this choice to personalize your experience. You can modify it later.",
  "Continuer avec Google": "Continue with Google",
  "Mon compte": "My account",
  "Accédez à votre espace client.": "Access your customer area.",
  "Connexion": "Connection",
  "Connexion...": "Connection...",
  "Créer un compte": "Create an account",
  "email": "e-mail",
  "Mot de passe": "Password",
  "Mot de passe oublié ?": "Forgotten password?",
  "Pas encore de compte ?": "No account yet?",
  "Conditions générales": "General conditions",
  "Détail commande": "Order details",
  "Inscription": "Registration",
  "Livraison & retours": "Delivery & returns",
  "Livraison et paiement": "Delivery and payment",
  "Mot de passe oublié": "Forgotten password",
  "Nouveau mot de passe": "New Password",
  "Panier": "Basket",
  "Politique de confidentialité": "Privacy Policy",
  "France metropolitaine": "Metropolitan France",
  "Livraison fiable avec": "Reliable delivery with",
  "Livraison offerte des 45 EUR d'achat.": "Free delivery of 45 EUR purchase.",
  "Affiche la barre latérale mobile.": "Shows the mobile sidebar.",
  "Aucun ingrédient": "No ingredients",
  "Chargement de votre wishlist...": "Loading your wishlist...",
  "Votre wishlist": "Your wishlist",
  "Votre wishlist est vide.": "Your wishlist is empty.",
  "Impossible d'ajouter cette création à votre wishlist.": "Unable to add this creation to your wishlist.",
  "Impossible de calculer les réductions.": "Unable to calculate discounts.",
  "Impossible de récupérer le panier.": "Unable to recover the basket.",
  "Mon mélange": "My mix",
  "Votre création a bien été ajoutée à votre wishlist.": "Your creation has been added to your wishlist.",
  "Bergamote de Calabre": "Calabrian Bergamot",
  "Bien-être": "Well-being",
  "Bleuet des Champs": "Cornflower",
  "Caramel Beurre Salé": "Salted Butter Caramel",
  "Choisissez votre fondement — le cœur de votre création": "Choose your foundation — the heart of your creation",
  "Citron de Menton": "Menton lemon",
  "Clarté": "Clarity",
  "Des notes fruitées naturellement sucrées": "Naturally sweet fruity notes",
  "Détente": "Relaxation",
  "Détox": "Detox",
  "Écorce de cannelle chaude et épicée": "Warm and Spicy Cinnamon Bark",
  "Écorces d'orange douces et parfumées": "Sweet and fragrant orange peels",
  "Élégance": "Elegance",
  "Énergie douce": "Soft energy",
  "Énergie durable": "Sustainable energy",
  "Équilibre": "Balance",
  "Évasion": "Escape",
  "Feuilles de menthe fraîche et intense": "Fresh and intense mint leaves",
  "Feuilles de sauge aux vertus purifiantes": "Sage leaves with purifying properties",
  "Finalisez avec des notes parfumées uniques, 100% naturelles, certifiées BIO. Jusqu'à 2 arômes par création.": "Finalize with unique scent notes, 100% natural, certified ORGANIC. Up to 2 flavors per creation.",
  "Fleurs bleues délicates aux vertus apaisantes": "Delicate blue flowers with soothing properties",
  "Fleurs d'hibiscus acidulées et rafraîchissantes": "Tangy and refreshing hibiscus flowers",
  "Fleurs de camomille douces et apaisantes": "Soft and soothing chamomile flowers",
  "Fleurs de jasmin parfumées et enivrantes": "Fragrant and intoxicating jasmine flowers",
  "Fleurs de lavande provençale aux vertus relaxantes": "Provencal lavender flowers with relaxing properties",
  "Fraîcheur": "Freshness",
  "Fraise des Bois": "Wild strawberry",
  "Framboises acidulées et fruitées": "Tart and fruity raspberries",
  "Gousse de vanille sucrée et crémeuse": "Sweet and creamy vanilla bean",
  "Herbe citronnée rafraîchissante": "Refreshing lemon herb",
  "Le plus délicat des thés, aux notes florales subtiles": "The most delicate of teas, with subtle floral notes",
  "Les vertus naturelles des plantes médicinales": "The natural virtues of medicinal plants",
  "Mangue exotique aux notes sucrées et crémeuses": "Exotic mango with sweet and creamy notes",
  "Maté argentin aux notes herbacées et légèrement amères": "Argentinian mate with herbaceous and slightly bitter notes",
  "Maté Vert": "Green Mate",
  "Mémoire": "Memory",
  "Menthe Poivrée": "Peppermint",
  "Métabolisme": "Metabolism",
  "Miel de Lavande": "Lavender Honey",
  "Miel floral doux et naturel": "Sweet and natural floral honey",
  "Morceaux de fraise sucrés et parfumés": "Sweet and fragrant strawberry pieces",
  "Morceaux de pomme croquants et sucrés": "Crunchy and sweet apple pieces",
  "Myrtilles sauvages aux notes boisées": "Wild blueberries with woody notes",
  "Noix de Coco": "Coconut",
  "Notes d'amande crémeuse et réconfortante": "Creamy, comforting almond notes",
  "Notes exotiques de coco crémeuse": "Exotic notes of creamy coconut",
  "Notes gourmandes de caramel fondant": "Gourmet notes of melting caramel",
  "Pêche Blanche": "White Fishing",
  "Pêche juteuse et délicatement sucrée": "Juicy and delicately sweet peach",
  "Pétales de rose aux notes délicates et apaisantes": "Rose petals with delicate and soothing notes",
  "Racine de gingembre piquante et tonifiante": "Pungent and invigorating ginger root",
  "Racine de réglisse sucrée et caractéristique": "Sweet and characteristic licorice root",
  "Réconfort": "Comfort",
  "Réglisse Douce": "Sweet Licorice",
  "Réveil": "Awakening",
  "Rooibos sud-africain sans théine, doux et sucré": "South African rooibos without theine, mild and sweet",
  "Rose de Damas": "Damask rose",
  "Sans théine": "Without theine",
  "Santé": "Health",
  "Sérénité": "Serenity",
  "Thé Blanc Pai Mu Tan": "Pai Mu Tan White Tea",
  "Thé Noir Assam": "Assam Black Tea",
  "Thé noir corsé aux notes maltées et caramel": "Full-bodied black tea with malty and caramel notes",
  "Thé semi-oxydé aux notes orchidées et beurre": "Semi-oxidized tea with orchid and butter notes",
  "Thé vert japonais délicat aux notes végétales fraîches": "Delicate Japanese green tea with fresh vegetal notes",
  "Thé Vert Sencha": "Sencha Green Tea",
  "Thym aromatique aux propriétés antiseptiques": "Aromatic thyme with antiseptic properties",
  "Une touche florale délicate et poétique": "A delicate and poetic floral touch",
  "Verveine citronnée et apaisante": "Soothing lemon verbena",
  "Vitalité": "Vitality",
  "Vitaminé": "Vitamin",
  "Vitaminé C": "Vitamin C",
  "Vivacité": "Liveliness",
  "Zeste de citron frais et tonifiant": "Fresh and invigorating lemon zest",
  "thé": "tea",
  "Comment ça marche": "How it works",
  "Témoignages": "Testimonials",
  "Des essentiels pour sublimer": "Essentials to sublimate",
  "Votre Rituel": "Your Ritual",
  "Retrouvez une sélection d’accessoires pour accompagner vos créations.": "Find a selection of accessories to accompany your creations.",
  "Voir tous les accessoires": "See all accessories",
  "Complétez votre dégustation avec nos essentiels.": "Complete your tasting with our essentials.",
  "Image précédente": "Previous image",
  "Ouvrir la galerie": "Open gallery",
  "Ajouter une nouvelle adresse": "Add a new address",
  "Ajoutez ou modifiez des adresses complémentaires.": "Add or modify additional addresses.",
  "Aucune adresse supplémentaire.": "No additional address.",
  "Gérez vos adresses par défaut.": "Manage your default addresses.",
  "Mes adresses supplémentaires": "My additional addresses",
  "Adresse de facturation": "Billing address",
  "Adresse de livraison": "Delivery address",
  "Aucune commande récente.": "No recent orders.",
  "Civilité :": "Civility:",
  "Dernières commandes passées sur My Own Tea.": "Latest orders placed on My Own Tea.",
  "Email :": "Email:",
  "Informations associées à votre compte.": "Information associated with your account.",
  "Mes informations personnelles": "My personal information",
  "Mon carnet d'adresses": "My address book",
  "Nous sommes là pour vous aider.": "We are here to help you.",
  "Prénom :": "First name:",
  "Voir toutes mes commandes": "See all my orders",
  "Vos adresses de livraison et de facturation par défaut.": "Your default shipping and billing addresses.",
  "Changer mon email": "Change my email",
  "Changer mon mot de passe": "Change my password",
  "Confirmer le nouveau mot de passe *": "Confirm new password *",
  "Email invalide": "Invalid email",
  "Gère tes emails marketing. Les emails transactionnels restent actifs.": "Manage your marketing emails. Transactional emails remain active.",
  "Informations mises à jour.": "Updated information.",
  "Le changement de mot de passe n'est pas disponible pour ce compte.": "Password change is not available for this account.",
  "Le nouveau mot de passe doit contenir 8 caractères minimum.": "The new password must contain at least 8 characters.",
  "Les mots de passe ne correspondent pas.": "Passwords do not match.",
  "Merci de renseigner tous les champs du mot de passe.": "Please complete all password fields.",
  "Mettez à jour vos informations personnelles.": "Update your personal information.",
  "Mot de passe actuel *": "Current password *",
  "Mot de passe requis": "Password required",
  "Nouveau mot de passe *": "New Password *",
  "Préférences email": "Email preferences",
  "Relances et rappels": "Reminders and reminders",
  "Téléphone": "Phone",
  "Adresse indisponible": "Address unavailable",
  "Annulé": "Canceled",
  "Boutique en ligne de thés & infusions": "Online store of teas & infusions",
  "Carte bancaire sécurisée (via Stripe)": "Secure bank card (via Stripe)",
  "Commande introuvable.": "Order not found.",
  "Conservez ce document pour votre comptabilité et vos archives.": "Keep this document for your accounting and records.",
  "Date d'émission": "Issue date",
  "Désignation": "Designation",
  "Document de facturation client pour la commande": "Customer invoicing document for order",
  "Échoué": "Failed",
  "Émetteur": "Issuer",
  "Facturé à": "Billed to",
  "Facture générée automatiquement depuis votre espace client le": "Invoice generated automatically from your customer area on",
  "Imprimer la facture": "Print the invoice",
  "Livré à": "Delivered to",
  "Méthode :": "Method:",
  "Mode de livraison :": "Delivery method:",
  "Moyen détaillé :": "Detailed means:",
  "Paiement et livraison": "Payment and delivery",
  "Paiement via Apple Pay": "Payment via Apple Pay",
  "Paiement via Google Pay": "Payment via Google Pay",
  "Paiement via portefeuille PayPal": "Payment via PayPal wallet",
  "Payé": "Paid",
  "Qté": "Qty",
  "Référence commande": "Order reference",
  "Référence transport :": "Transport reference:",
  "Remboursé": "Refunded",
  "Statut commande": "Order status",
  "Statut de paiement :": "Payment status:",
  "Moyen de paiement :": "Payment method:",
  "Passée le": "Passed the",
  "unité": "unit",
  "Référence et suivi transporteur :": "Carrier reference and tracking:",
  "Suivre le colis": "Track the package",
  "Aucune commande trouvée.": "No orders found.",
  "Résultats par page": "Results per page",
  "Retrouvez l'historique complet de vos commandes.": "Find the complete history of your orders.",
  "Voir la commande": "View order",
  "Email:": "E-mail:",
  "Prénom:": "First name:",
  "(estimée)": "(estimated)",
  "€ / unité": "€/unit",
  "1. Panier": "1. Shopping cart",
  "2. Livraison et paiement": "2. Delivery and payment",
  "À confirmer": "To be confirmed",
  "Ajouter un code de réduction": "Add a discount code",
  "Calcul des réductions...": "Calculation of reductions...",
  "Chargement du panier": "Loading cart",
  "Code appliqué:": "Code applied:",
  "Code non appliqué:": "Code not applied:",
  "Continuer à créer": "Continue to create",
  "Créer Mon Mélange": "Create My Blend",
  "Créez un mélange unique et ajoutez-le ici pour le commander plus tard.": "Create a unique blend and add it here to order later.",
  "Entrez votre code": "Enter your code",
  "et les frais de port sont recalculés à l'étape suivante.": "and the shipping costs are recalculated in the next step.",
  "Impossible de créer la session d'abonnement.": "Failed to create subscription session.",
  "Les taxes sont incluses": "Taxes are included",
  "Livraison gratuite débloquée": "Free delivery unlocked",
  "Livraison rapide en France et en Belgique": "Fast delivery in France and Belgium",
  "Récupération de vos articles en cours...": "Recovering your items in progress...",
  "Seuil France:": "French threshold:",
  "Veuillez séparer les abonnements des autres articles pour le paiement.": "Please separate subscriptions from other items for payment.",
  "Veuillez vous connecter pour acheter des accessoires ou des abonnements.": "Please log in to purchase accessories or subscriptions.",
  "Votre Panier": "Your Cart",
  "Votre panier est vide": "Your basket is empty",
  "Livraison fiable": "Reliable delivery",
  "Paiement sécurisé": "Secure payment",
  "Satisfait ou remboursé": "Satisfied or refunded",
  "Sécurité & garanties": "Security & guarantees",
  "Suivi et livraison soignée": "Careful tracking and delivery",
  "Aucun point relais trouvé pour cette zone. Vérifiez le pays et le code postal puis relancez la recherche.": "No relay point found for this area. Check the country and postal code then search again.",
  "Code postal et pays requis pour rechercher un point relais.": "Postal code and country required to search for a relay point.",
  "Continuer vers le paiement": "Continue to payment",
  "Coordonnées du destinataire": "Recipient details",
  "En point relais, l'adresse de facturation reste requise.": "At relay points, the billing address remains required.",
  "Enregistrer cette adresse comme adresse de facturation par défaut": "Save this address as your default billing address",
  "Enregistrer cette adresse comme adresse de livraison par défaut": "Save this address as your default delivery address",
  "Fermé": "Farm",
  "Formulaire domicile : même structure que votre carnet d'adresses.": "Home form: same structure as your address book.",
  "Impossible de charger les points relais.": "Unable to load relay points.",
  "Impossible de charger Stripe.": "Unable to load Stripe.",
  "Impossible de préparer le paiement.": "Unable to prepare payment.",
  "Instruction spéciale": "Special instruction",
  "Instruction spéciale pour le vendeur...": "Special instruction for the seller...",
  "La facturation utilisera la même adresse que la livraison.": "Billing will use the same address as delivery.",
  "La livraison en point relais est indisponible pour le moment.": "Delivery to relay points is currently unavailable.",
  "Le paiement a échoué.": "The payment failed.",
  "Le point relais sélectionné est utilisé pour l'adresse de livraison.": "The selected relay point is used for the delivery address.",
  "Le téléphone doit être au format +33612345678.": "The phone must be in the format +33612345678.",
  "Les points relais ont été trouvés, mais aucune coordonnée GPS n'a été fournie pour afficher la carte.": "The relay points were found, but no GPS coordinates were provided to display the map.",
  "livraison": "delivery",
  "Mode de livraison": "Delivery method",
  "Modifier mes informations": "Edit my information",
  "Paiement en cours...": "Payment in progress...",
  "Payer ma commande": "Pay for my order",
  "Pays, code postal et ville sont dérivés de votre recherche de point relais.": "Country, postal code and city are derived from your relay point search.",
  "Point relais sélectionné :": "Selected relay point:",
  "Préparation du paiement...": "Preparing payment...",
  "Récapitulatif": "Summary",
  "Recherche des villes pour ce code postal...": "Searching cities for this postal code...",
  "Renseignez vos adresses puis finalisez le paiement.": "Enter your addresses then finalize the payment.",
  "Sélectionnez un pays": "Select a country",
  "Sélectionnez un pays d'Europe *": "Select a country in Europe *",
  "Stripe est en cours de chargement.": "Stripe is loading.",
  "Les paiements express (Apple Pay / Google Pay) ne sont pas disponibles dans cet environnement. Ils nécessitent un domaine HTTPS vérifié sur Stripe et un navigateur/appareil compatible.": "Express payments (Apple Pay / Google Pay) are not available in this environment. They require a verified HTTPS domain on Stripe and a compatible browser/device.",
  "Téléphone (+336...) *": "Telephone (+336...) *",
  "Utiliser la même adresse pour la facturation": "Use the same address for billing",
  "Veuillez sélectionner un point relais.": "Please select a relay point.",
  "Ces conditions encadrent l’utilisation de la boutique My Own Tea, la passation de commande et les obligations réciproques entre le client et la boutique.": "These conditions govern the use of the My Own Tea store, the placing of an order and the reciprocal obligations between the customer and the store.",
  "Droit de rétractation": "Right of withdrawal",
  "Email: contact@myowntea.fr": "Email: contact@myowntea.fr",
  "En cas d’anomalie de livraison, le client doit signaler le problème rapidement au support.": "In the event of a delivery anomaly, the customer must report the problem quickly to support.",
  "La commande est remise au transporteur une fois préparée. Le client reçoit un lien de suivi.": "The order is handed over to the carrier once prepared. The customer receives a tracking link.",
  "Le client vérifie les informations de livraison et de facturation avant paiement": "Customer verifies delivery and billing information before payment",
  "Le droit de rétractation s’applique aux produits standards selon la réglementation en vigueur.": "The right of withdrawal applies to standard products according to current regulations.",
  "Le paiement est sécurisé via Stripe.": "Payment is secure via Stripe.",
  "Le suivi des statuts est disponible dans l’espace Mon compte": "Status tracking is available in the My Account area",
  "Les créations personnalisées sont réalisées à partir des ingrédients choisis par le client dans l’atelier de création.": "Personalized creations are made from ingredients chosen by the customer in the creation workshop.",
  "Les prix sont affichés en euros TTC. Les frais de livraison sont calculés au checkout selon les paramètres boutique et la zone de livraison.": "Prices are displayed in euros including tax. Delivery costs are calculated at checkout according to the store parameters and the delivery area.",
  "Les produits personnalisés confectionnés à la demande peuvent être exclus, sauf défaut ou non-conformité.": "Personalized products made to order may be excluded, unless there is a defect or non-compliance.",
  "Livraison et transfert de responsabilité": "Delivery and transfer of responsibility",
  "Prix et paiement": "Price and payment",
  "Réclamation: préciser numéro de commande et motif": "Complaint: specify order number and reason",
  "Suivi commande: Mon compte > Commandes": "Order tracking: My account > Orders",
  "Un email de confirmation est envoyé après validation": "A confirmation email is sent after validation",
  "Une commande est validée après confirmation du paiement.": "An order is validated after confirmation of payment.",
  "Adresse": "Address",
  "Avant de nous contacter": "Before contacting us",
  "Consultez la FAQ pour les réponses immédiates": "Check the FAQ for immediate answers",
  "Du lundi au vendredi, de 9h à 18h (heure de Paris).": "Monday to Friday, 9 a.m. to 6 p.m. (Paris time).",
  "Email principal: contact@myowntea.fr": "Main email: contact@myowntea.fr",
  "Horaires de réponse": "Response times",
  "My Own Tea, 12 Rue des Arômes, 75011 Paris, France.": "My Own Tea, 12 Rue des Arômes, 75011 Paris, France.",
  "Notre équipe vous accompagne sur vos commandes, vos créations personnalisées et la gestion de votre compte.": "Our team supports you with your orders, your personalized creations and the management of your account.",
  "Nous écrire": "Write to us",
  "Objet recommandé: Livraison / Paiement / Produit / Compte": "Recommended subject: Delivery / Payment / Product / Account",
  "Pour une question RGPD, précisez “Données personnelles” dans l’objet": "For a GDPR question, specify “Personal data” in the subject",
  "Support commandes: inclure votre numéro de commande (ORD-...)": "Order support: include your order number (ORD-...)",
  "Vérifiez le suivi dans Mon compte > Commandes": "Check tracking in My Account > Orders",
  "Aucun ingrédient.": "No ingredients.",
  "Choisissez votre format": "Choose your format",
  "Création artisanale": "Artisanal creation",
  "Détails supplémentaires": "Additional Details",
  "Ingrédient": "Ingredient",
  "Moments de la journée": "Times of the day",
  "Personnaliser ce mélange": "Customize this mix",
  "Aucune création disponible pour le moment.": "No creations available at the moment.",
  "Chargement des créations...": "Loading creations...",
  "Créations de la communauté": "Community creations",
  "Découvrez les mélanges les plus inspirants, issus des commandes de la communauté. Ajoutez-les à votre panier et personnalisez-les ensuite.": "Discover the most inspiring blends, sourced from community orders. Add them to your cart and then personalize them.",
  "Modifier dans l'atelier": "Edit in the workshop",
  "12 g/L (≈ 3 g pour 25 cl)": "12 g/L (≈ 3 g for 25 cl)",
  "Ajouter à ma wishlist": "Add to my wishlist",
  "Ajouter au Panier": "Add to Cart",
  "Ajouter la création à la wishlist": "Add the creation to the wishlist",
  "Ajoutez au moins un ingrédient hors arôme": "Add at least one non-flavoring ingredient",
  "Aperçu de la tasse": "Cup overview",
  "Aucun ingrédient disponible pour cette catégorie.": "No ingredients available for this category.",
  "Chargement des ingrédients...": "Loading ingredients...",
  "Complétez votre sélection pour finaliser": "Complete your selection to finalize",
  "Corps/texture en bouche. Allant de léger et fluide à dense, “velouté”, presque sirupeux.": "Body/texture in the mouth. Ranging from light and fluid to dense, “velvety”, almost syrupy.",
  "Créez Votre": "Create your",
  "Donnez une identité à votre mélange. Il mérite un nom aussi unique que sa composition.": "Give your mixture an identity. It deserves a name as unique as its composition.",
  "Épaisseur": "Thickness",
  "Ex: Mon Éveil Matinal": "Ex: My Morning Awakening",
  "Fermer les détails": "Close details",
  "Indique la puissance des saveurs de ce thé. De subtil et délicat à un goût franc et corsé.": "Indicates the power of the flavors of this tea. From subtle and delicate to a frank and full-bodied taste.",
  "Informations de préparation indisponibles.": "Preparation information unavailable.",
  "Infusion sans base = mélange plus concentré, prix ajusté": "Infusion without base = more concentrated mixture, adjusted price",
  "Intensité": "Intensity",
  "L'Atelier du Maître Mélangeur": "The Master Blender's Workshop",
  "Limite atteinte: 2 arômes maximum": "Limit reached: 2 flavors maximum",
  "Mon Mélange": "My Blend",
  "Nommez Votre Création": "Name Your Creation",
  "Perception de douceur naturelle (sans sucre ajouté). Allant de sec/peu doux à nettement doux et gourmand.": "Perception of natural sweetness (no added sugar). Ranging from dry/not very sweet to distinctly sweet and gourmand.",
  "Persistante aromatique après avoir avalé. Allant de vite disparue à très longue, évolutive et expressive.": "Persistent aromatic after swallowing. Ranging from quickly disappearing to very long, evolving and expressive.",
  "Retirer de ma création": "Remove from my creation",
  "Sensation “savoureuse” et rondeur en bouche. Allant de quasi absent à très présent, rond et enveloppant.": "“Tasty” sensation and roundness in the mouth. Ranging from almost absent to very present, round and enveloping.",
  "Sucrosité": "Sweetness",
  "Suivez les étapes et assemblez votre composition parfaite. Jusqu'à 10 ingrédients pour un mélange harmonieux.": "Follow the steps and assemble your perfect composition. Up to 10 ingredients for a harmonious blend.",
  "Température d'infusion": "Brew Temperature",
  "Utiliser dans ma création": "Use in my creation",
  "Votre Création": "Your Creation",
  "Votre Recette": "Your Recipe",
  "Comment créer mon infusion personnalisée ?": "How do I create my personalized infusion?",
  "Comment gérer mes emails marketing ?": "How do I manage my marketing emails?",
  "Contactez-nous avec votre numéro de commande. Nous vous répondons avec une solution adaptée (correction, renvoi, remboursement selon le cas).": "Contact us with your order number. We respond to you with a suitable solution (correction, resend, refund depending on the case).",
  "Désinscription depuis le footer ou le lien en bas des emails": "Unsubscribe from the footer or the link at the bottom of the emails",
  "Gestion complète des préférences dans Mon compte > Informations": "Complete management of preferences in My Account > Information",
  "Inscription depuis le footer avec consentement explicite": "Registration from the footer with explicit consent",
  "Je rencontre un problème sur ma commande": "I have a problem with my order",
  "Le mode “infusion sans base” est pris en charge avec une formule tarifaire dédiée pour garantir une composition concentrée et cohérente.": "The “baseless infusion” mode is supported with a dedicated pricing plan to guarantee a concentrated and consistent composition.",
  "Le paiement en ligne est sécurisé via Stripe.": "Online payment is secure via Stripe.",
  "Oui. Dès que le colis est expédié, un numéro de suivi et un lien transporteur sont disponibles dans votre espace Mon compte.": "Yes. As soon as the package is shipped, a tracking number and a carrier link are available in your My Account space.",
  "Puis-je suivre ma commande ?": "Can I track my order?",
  "Quels paiements acceptez-vous ?": "What payments do you accept?",
  "Réponses rapides aux questions les plus fréquentes sur la création de mélange, la commande, la livraison et le compte client.": "Quick answers to the most frequently asked questions about mix creation, ordering, delivery and customer account.",
  "Utilisez l’atelier de création pour choisir vos ingrédients. Le prix se met à jour automatiquement selon la composition.": "Use the creation workshop to choose your ingredients. The price updates automatically depending on the composition.",
  "12 Rue des Arômes": "12 Rue des Arômes",
  "75011 Paris, France": "75011 Paris, France",
  "Adresse email invalide.": "Invalid email address.",
  "Choisir la langue et le pays": "Choose language and country",
  "Créez votre thé signature à partir d'ingrédients bio soigneusement sélectionnés. Une expérience unique de mélange personnalisé.": "Create your signature tea from carefully selected organic ingredients. A unique personalized blending experience.",
  "Données traitées selon la": "Data processed according to the",
  "English (Belgique)": "English (Belgium)",
  "English (France)": "English (France)",
  "Impossible de vous inscrire pour le moment.": "Unable to register at this time.",
  "Inscription à la newsletter confirmée.": "Newsletter subscription confirmed.",
  "Inscription confirmée.": "Registration confirmed.",
  "Inscription...": "Registration...",
  "Merci de renseigner votre email.": "Please enter your email.",
  "politique de confidentialité": "Privacy Policy",
  "Recevez nos recettes exclusives et offres spéciales": "Receive our exclusive recipes and special offers",
  "Rejoignez Notre Communauté": "Join Our Community",
  "Votre email": "Your email",
  "connexion": "connection",
  "Envoyer le lien": "Send link",
  "Impossible d'envoyer l'email de réinitialisation pour le moment.": "Unable to send reset email at this time.",
  "Retour à la": "Return to",
  "Saisissez votre email pour recevoir un lien de réinitialisation.": "Enter your email to receive a reset link.",
  "Si un compte existe, un email vous a été envoyé.": "If an account exists, an email has been sent to you.",
  "Commencer Ma Création": "Start My Creation",
  "Composez Votre": "Dial Your",
  "Devenez l'architecte de vos saveurs. Sélectionnez les meilleurs ingrédients parmi nos trésors botaniques et créez un mélange qui vous ressemble.": "Become the architect of your flavors. Select the best ingredients from our botanical treasures and create a blend that suits you.",
  "Échantillons gratuits": "Free samples",
  "L'Art du Mélange": "The Art of Mixing",
  "Livraison offerte dès": "Free delivery from",
  "Thé Unique": "Unique Tea",
  "Comment Ça Marche": "How It Works",
  "Créez Votre Mélange": "Create Your Mix",
  "De L'Idée à": "From Idea to",
  "Donnez un nom unique à votre création. Chaque mélange est préparé à la main et emballé dans un sachet élégant avec votre étiquette personnalisée.": "Give your creation a unique name. Each blend is prepared by hand and packaged in a stylish pouch with your personalized label.",
  "Livraison rapide et soignée chez vous ou offrez-le à un proche. Votre mélange signature, prêt à être dégusté et partagé.": "Fast and careful delivery to your home or offer it to a loved one. Your signature blend, ready to enjoy and share.",
  "Notre assistant intelligent vous guide pour créer une harmonie parfaite. Jusqu'à 10 ingrédients pour un équilibre optimal de saveurs et de bienfaits.": "Our intelligent assistant guides you to create perfect harmony. Up to 10 ingredients for an optimal balance of flavors and benefits.",
  "Parcourez notre collection de 40+ ingrédients bio soigneusement sourcés. Choisissez votre base, ajoutez des fleurs, des fruits, des plantes et des arômes selon vos envies.": "Browse our collection of 40+ carefully sourced organic ingredients. Choose your base, add flowers, fruits, plants and aromas as you wish.",
  "Personnalisez Votre Packaging": "Personalize Your Packaging",
  "Quatre étapes simples pour créer le thé de vos rêves, préparé avec soin et expédié directement chez vous.": "Four simple steps to create the tea of ​​your dreams, carefully prepared and shipped straight to your door.",
  "Recevez Votre Création": "Receive Your Creation",
  "Sélectionnez Vos Ingrédients": "Select Your Ingredients",
  "Votre Tasse": "Your Cup",
  "Dernière mise à jour :": "Last update:",
  "Confirmation d’expédition envoyée par email après création du bordereau": "Shipping confirmation sent by email after creation of the slip",
  "Contactez-nous via la page Contact avec votre numéro de commande": "Contact us via the Contact page with your order number",
  "Délais indicatifs": "Indicative deadlines",
  "Le remboursement est déclenché après réception et validation du retour": "The refund is triggered after receipt and validation of the return",
  "Le suivi peut être consulté depuis Mon compte > Commandes": "Tracking can be viewed from My Account > Orders",
  "Les options affichées au checkout dépendent du pays, du code postal et des offres transport disponibles en temps réel.": "The options displayed at checkout depend on the country, postal code and transport offers available in real time.",
  "Modes de livraison": "Delivery methods",
  "Notre équipe vous confirme l’éligibilité et la marche à suivre": "Our team confirms eligibility and the procedure to follow",
  "Nous proposons la livraison à domicile et la livraison en point relais via Mondial Relay (intégration Boxtal).": "We offer home delivery and delivery to relay points via Mondial Relay (Boxtal integration).",
  "Point relais: choix du relais sur carte depuis le checkout": "Relay point: choice of relay on map from checkout",
  "Domicile: suivi transporteur en ligne": "Home: online carrier tracking",
  "Pour les accessoires et produits standards: vous disposez de 14 jours après réception pour demander un retour.": "For standard accessories and products: you have 14 days after receipt to request a return.",
  "Pour les créations personnalisées (mélanges composés à la demande): les retours ne sont possibles qu’en cas de défaut qualité ou d’erreur de préparation.": "For personalized creations (mixes made on demand): returns are only possible in the event of a quality defect or preparation error.",
  "Préparation atelier: 1 à 2 jours ouvrés": "Workshop preparation: 1 to 2 working days",
  "Retours et réclamations": "Returns and complaints",
  "Retrouvez ici les modalités de livraison de My Own Tea, les délais estimés et la procédure de retour. Les coûts appliqués au checkout sont pilotés depuis les paramètres boutique.": "Find here the delivery terms of My Own Tea, the estimated times and the return procedure. The costs applied to checkout are controlled from the store settings.",
  "Transit France métropolitaine: 2 à 4 jours ouvrés": "Transit mainland France: 2 to 4 working days",
  "Revenir à l&apos;accueil maintenant": "Return to home now",
  "Session terminée": "Session ended",
  "Vous allez être redirigé(e) vers l&apos;accueil dans": "You will be redirected to the reception in",
  "Vous êtes déconnecté(e)": "You are logged out",
  "Contacter le support": "Contact support",
  "Nous effectuons une mise à jour pour améliorer votre expérience. Le checkout est temporairement indisponible et reviendra très vite.": "We are updating to improve your experience. Checkout is temporarily unavailable and will return very soon.",
  "Retour à l&apos;accueil": "Back to home",
  "Créer Mon Thé": "Create My Tea",
  "Créer mon thé dans l'atelier du maître mélangeur": "Create my tea in the master blender's workshop",
  "Créer un mélange": "Create a mix",
  "Créer mon mélange": "Create my mix",
  "Le contenu demandé n&apos;existe pas ou a été déplacé.": "The requested content does not exist or has been moved.",
  "Vérification de la redirection...": "Checking the redirection...",
  "Commande introuvable": "Order not found",
  "Contactez-nous avec votre numéro de commande pour toute demande.": "Contact us with your order number for any requests.",
  "Finalisation de votre commande…": "Finalizing your order…",
  "Merci pour votre commande !": "Thank you for your order!",
  "Nous n'avons pas trouvé cette commande. Vérifiez votre URL ou retournez à l'accueil.": "We could not find this command. Check your URL or return to home.",
  "Numéro de commande": "Order number",
  "Réduction": "Reduction",
  "Retour à l'accueil": "Back to home",
  "Accès, rectification et suppression de vos données": "Access, rectification and deletion of your data",
  "Commande: contenu panier, paiements, statuts et suivi livraison": "Order: basket contents, payments, statuses and delivery tracking",
  "Compte client: identité, email, téléphone, adresses": "Customer account: identity, email, telephone, addresses",
  "Consentement RGPD et newsletter": "GDPR consent and newsletter",
  "Données collectées": "Data collected",
  "Envoi de newsletters et d’emails marketing uniquement avec consentement": "Sending newsletters and marketing emails only with consent",
  "Exécution des commandes et service après-vente": "Order fulfillment and after-sales service",
  "Finalités": "Purposes",
  "Gestion du compte client et des préférences email": "Management of customer account and email preferences",
  "L’inscription newsletter depuis le footer nécessite un consentement explicite.": "Newsletter registration from the footer requires explicit consent.",
  "Limitation ou opposition au traitement marketing": "Limitation or opposition to marketing processing",
  "Modification possible à tout moment depuis Mon compte > Informations": "Modification possible at any time from My account > Information",
  "Newsletter: email, consentement marketing, statut d’opt-in/out": "Newsletter: email, marketing consent, opt-in/out status",
  "Nous stockons l’état d’abonnement (opt-in/out) et un journal des événements de consentement (date, source, données techniques associées).": "We store subscription status (opt-in/out) and a log of consent events (date, source, associated technical data).",
  "Nous traitons vos données personnelles uniquement pour opérer la boutique, exécuter vos commandes et, avec consentement, vous envoyer des communications marketing.": "We process your personal data only to operate the store, fulfill your orders and, with consent, send you marketing communications.",
  "Opt-in: inscription newsletter": "Opt-in: newsletter registration",
  "Opt-out: désinscription footer, préférences compte ou lien de désinscription email": "Opt-out: unsubscribe footer, account preferences or email unsubscribe link",
  "Pour exercer vos droits, contactez-nous à contact@myowntea.fr.": "To exercise your rights, contact us at contact@myowntea.fr.",
  "Retrait du consentement à tout moment": "Withdrawal of consent at any time",
  "Vos droits": "Your rights",
  "Création...": "Creation...",
  "Créer mon compte": "Create my account",
  "Déjà inscrit ?": "Already registered?",
  "Email et mot de passe requis.": "Email and password required.",
  "Enregistrez votre espace client.": "Register your customer area.",
  "Format attendu pour le téléphone : +33612345678.": "Expected format for the phone: +33612345678.",
  "Impossible de créer le compte.": "Unable to create account.",
  "Je souhaite recevoir les emails de relances et rappels": "I would like to receive follow-up emails and reminders",
  "Je souhaite recevoir les emails marketing": "I would like to receive marketing emails",
  "Le mot de passe doit contenir 8 caractères minimum.": "The password must contain at least 8 characters.",
  "Merci de renseigner votre prénom et votre nom.": "Please provide your first and last name.",
  "Merci de sélectionner une civilité.": "Please select a title.",
  "Prénom": "First name",
  "Téléphone (+33...)": "Telephone (+33...)",
  "Ce lien de réinitialisation est invalide ou expiré.": "This reset link is invalid or expired.",
  "Choisissez un nouveau mot de passe sécurisé.": "Choose a new secure password.",
  "Confirmer le mot de passe": "Confirm password",
  "Impossible de réinitialiser le mot de passe.": "Unable to reset password.",
  "Impossible de vérifier le lien de réinitialisation.": "Unable to check reset link.",
  "Le mot de passe doit contenir au moins 8 caractères.": "The password must contain at least 8 characters.",
  "Lien invalide. Merci de refaire une demande de réinitialisation.": "Invalid link. Please make a reset request again.",
  "Mettre à jour le mot de passe": "Update password",
  "Vérification du lien...": "Checking the link...",
  "Votre mot de passe a été réinitialisé. Vous pouvez maintenant vous connecter.": "Your password has been reset. You can now log in.",
  "Aucun abonnement disponible pour le moment.": "No subscriptions available at the moment.",
  "Chargement des abonnements...": "Loading subscriptions...",
  "Facturation tous les": "Billing every",
  "Impossible de créer la session d’abonnement.": "Failed to create subscription session.",
  "Recevez vos créations favorites chaque mois, sans y penser. Choisissez votre formule et profitez d’une infusion continue.": "Receive your favorite creations every month, without thinking about it. Choose your formula and enjoy continuous infusion.",
  "Veuillez vous connecter pour souscrire.": "Please log in to subscribe.",
  "Amatrice de thé": "Tea lover",
  "Émilie Rousseau": "Emilie Rousseau",
  "Énergie Collective": "Collective Energy",
  "Épices d'Orient": "Oriental spices",
  "Étudiante": "Student",
  "Ils Ont Créé": "They Created",
  "Ingrédients bio": "Organic ingredients",
  "J'ai offert un mélange personnalisé à mon équipe. Le packaging est magnifique et le goût est au rendez-vous. Un cadeau original !": "I offered a custom blend to my team. The packaging is magnificent and the taste is there. An original gift!",
  "La qualité des ingrédients est exceptionnelle. J'ai créé un mélange épicé pour accompagner mes desserts, et mes clients adorent !": "The quality of the ingredients is exceptional. I created a spicy mix to accompany my desserts, and my customers love it!",
  "Le prix est très raisonnable pour la qualité. J'adore pouvoir expérimenter différentes combinaisons selon mes humeurs !": "The price is very reasonable for the quality. I love being able to experiment with different combinations depending on my mood!",
  "Marc Lefèvre": "Marc Lefevre",
  "Mélange créé": "Mix created",
  "Mélanges créés": "Mixtures created",
  "Mon mélange \"Sérénité\" avec camomille et verveine est parfait après mes séances de yoga. Une vraie pause bien-être.": "My “Serenity” blend with chamomile and verbena is perfect after my yoga sessions. A real well-being break.",
  "Réveil en Provence": "Awakening in Provence",
  "Une expérience unique ! J'ai créé mon mélange \"Réveil en Provence\" avec de la lavande et du thé vert. C'est devenu mon rituel matinal indispensable.": "A unique experience! I created my “Réveil en Provence” blend with lavender and green tea. It has become my essential morning ritual.",
  "Aucune création classée disponible pour le moment.": "No classified creations available at the moment.",
  "Découvrez les créations les mieux classées de notre communauté et personnalisez-les dans l'atelier ou ajoutez les directement au panier.": "Discover the top-ranked creations from our community and personalize them in the workshop or add them directly to the cart.",
  "Erreur lors du chargement des créations": "Error loading creatives",
  "Le Top 3 de vos": "The Top 3 of your",
  "Sélection de la communauté #myowntea": "Selection of the #myowntea community",
  "Voir + de créations": "See more creations",
  "6 idées simples pour créer un mélange équilibré": "6 simple ideas to create a balanced mixture",
  "adresse précédente": "previous address",
  "Ajoutez au moins un ingrédient hors arôme.": "Add at least one non-flavoring ingredient.",
  "Alerte sécurité du compte": "Account security alert",
  "Ancien email": "Old email",
  "Annule automatiquement les commandes PENDING expirées sans paiement.": "Automatically cancels expired PENDING orders without payment.",
  "Besoin d’idées pour votre infusion ?": "Need ideas for your infusion?",
  "Bienvenue dans votre atelier infusion": "Welcome to your infusion workshop",
  "Blend personnalisé": "Custom Blend",
  "Boxtal non configuré, synchronisation ignorée": "Boxtal not configured, synchronization ignored",
  "Ce message est envoyé à des fins de vérification.": "This message is sent for verification purposes.",
  "Ceci est un email de test généré depuis l'administration.": "This is a test email generated from the administration.",
  "Cela fait un moment que nous ne vous avons pas vu.": "It's been a while since we've seen you.",
  "Cette remise est réservée à la première commande. Vous avez déjà une commande payée ou confirmée.": "This discount is reserved for the first order. You already have a paid or confirmed order.",
  "Commande annulée": "Order canceled",
  "Commande annulee automatiquement suite au statut transporteur": "Order automatically canceled following carrier status",
  "Commande confirmée": "Order confirmed",
  "Commande en préparation": "Order in preparation",
  "Commande expédiée": "Order shipped",
  "Commande livrée": "Order delivered",
  "Commande remboursée": "Order refunded",
  "Commencer ma création": "Start my creation",
  "Comment s’est passée votre dégustation ?": "How did your tasting go?",
  "Composez votre première infusion personnalisée en quelques clics.": "Compose your first personalized infusion in just a few clicks.",
  "Configuration de job introuvable": "Job configuration not found",
  "Conseil sécurité: mettez à jour votre mot de passe si cette action vous semble inhabituelle.": "Security Tip: Update your password if this action seems unusual to you.",
  "Conservez votre routine infusion sans interruption.": "Keep your infusion routine uninterrupted.",
  "Créez votre première infusion personnalisée": "Create your first personalized brew",
  "Cross-sell J+3 et demande d avis J+7 apres livraison.": "Cross-sell D+3 and request for opinion D+7 after delivery.",
  "Declenche les sequences welcome J0/J3.": "Triggers the welcome sequences J0/J3.",
  "Découvrez des idées complémentaires pour varier vos dégustations à la maison.": "Discover additional ideas to vary your tastings at home.",
  "Découvrez des suggestions adaptées à vos goûts": "Discover suggestions tailored to your tastes",
  "Découvrez les dernières nouveautés": "Discover the latest news",
  "Dernier rappel: finalisez votre panier": "Final reminder: finalize your basket",
  "Des inspirations pour bien commencer": "Inspiration to get you started",
  "Des nouveautés vous attendent": "New features await you",
  "Donner mon avis": "Give my opinion",
  "Email déjà utilisée": "Email already used",
  "Email déjà enregistré": "Email already registered",
  "Email et mot de passe requis": "Email and password required",
  "Email outbox": "Email outbox",
  "Email paniers abandonnés": "Email abandoned carts",
  "Email post-achat": "Post-purchase email",
  "Email réachat": "Email repurchase",
  "Email requis": "Email required",
  "Email requis.": "Email required.",
  "Email test du nouveau template": "Test email of the new template",
  "Email test My Own Tea": "Email test My Own Tea",
  "Email welcome": "Email welcome",
  "Email winback": "Email winback",
  "En attente de paiement": "Waiting for payment",
  "Envoi d’email introuvable": "Send email not found",
  "Envoie les emails transactionnels/marketing en attente avec retry.": "Sends pending transactional/marketing emails with retry.",
  "Erreur d’email de réinitialisation du mot de passe :": "Password reset email error:",
  "Erreur lors de l’envoi de l’email de test admin :": "Error sending the admin test email:",
  "Erreur lors de la création de l’ingrédient :": "Error creating the ingredient:",
  "Erreur lors de la mise à jour de l’ingrédient :": "Error updating ingredient:",
  "Erreur lors de la récupération de l’ingrédient :": "Error retrieving the ingredient:",
  "Erreur lors de la récupération des envois d’emails :": "Error when retrieving sent emails:",
  "Erreur lors de la récupération des métriques email :": "Error retrieving email metrics:",
  "Erreur lors de la relance d’envoi de l’email :": "Error when sending the email again:",
  "Erreur lors de la suppression de l’ingrédient :": "Error deleting ingredient:",
  "Exécution déjà en cours": "Execution already in progress",
  "Expédition introuvable": "Shipment not found",
  "Finalisez votre commande avant rupture": "Finalize your order before shortage",
  "Finalisez votre commande pour recevoir votre infusion sans attendre.": "Finalize your order to receive your infusion without delay.",
  "Il est peut-être temps de refaire le plein": "Maybe it's time to refill",
  "Il utilise le nouveau template harmonisé pour les emails clients.": "It uses the new harmonized template for customer emails.",
  "Ils sont encore disponibles: vous pouvez finaliser votre commande quand vous voulez.": "They are still available: you can finalize your order whenever you want.",
  "Impossible d'ajouter un article classique avec un abonnement.": "Unable to add a classic article with a subscription.",
  "Impossible d’enregistrer votre désinscription pour le moment.": "Unable to save your unsubscription at this time.",
  "Impossible d’enregistrer votre inscription pour le moment.": "Unable to save your registration at this time.",
  "Impossible de créer l’ingrédient": "Unable to create ingredient",
  "Impossible de mélanger un abonnement avec des articles classiques.": "Impossible to mix a subscription with classic articles.",
  "Impossible de mettre à jour l’email": "Unable to update email",
  "Impossible de mettre à jour l’ingrédient": "Unable to update ingredient",
  "Impossible de mettre à jour les préférences email": "Unable to update email preferences",
  "Impossible de récupérer l’ingrédient": "Unable to retrieve ingredient",
  "Impossible de récupérer les envois d’emails": "Unable to recover sent emails",
  "Impossible de récupérer les préférences email": "Unable to retrieve email preferences",
  "Ingrédient introuvable": "Ingredient not found",
  "Job désactivé": "Job disabled",
  "La livraison en point relais est indisponible pour cette adresse.": "Delivery to a relay point is unavailable for this address.",
  "Le consentement est requis pour l’inscription.": "Consent is required for registration.",
  "Le mélange ne peut pas contenir plus de 2 arômes.": "The mixture cannot contain more than 2 flavors.",
  "Le mélange ne peut pas dépasser 10 ingrédients.": "The mixture cannot exceed 10 ingredients.",
  "Le mot de passe de votre compte My Own Tea vient d'être modifié.": "Your My Own Tea account password has just been changed.",
  "Le paiement des abonnements doit être séparé des autres articles.": "Payment for subscriptions must be kept separate from other items.",
  "Le paiement doit être complété avant confirmation": "Payment must be completed before confirmation",
  "Le panier contient un autre abonnement.": "The cart contains another subscription.",
  "Le remboursement de votre commande a été enregistré.": "The refund for your order has been recorded.",
  "Les identifiants d’ingrédients sont requis": "Ingredient identifiers are required",
  "Les identifiants d’ingrédients sont requis pour les articles création du panier.": "Ingredient IDs are required for cart creation items.",
  "Lien de suivi transporteur": "Carrier tracking link",
  "Livraison à domicile": "Home delivery",
  "Merci pour votre dernière commande.": "Thank you for your last order.",
  "Mise à jour": "Update",
  "Mise à jour de commande": "Order update",
  "mot-dev-unsubscribe-secret": "word-dev-unsubscribe-secret",
  "Notre atelier vous guide pour trouver le bon équilibre de saveurs.": "Our workshop guides you to find the right balance of flavors.",
  "Nous aimerions vous revoir": "We would like to see you again",
  "Nous avons reçu une demande de réinitialisation du mot de passe de votre compte My Own Tea.": "We have received a request to reset your My Own Tea account password.",
  "Nous confirmons qu'une modification de l'adresse email a été effectuée sur votre compte My Own Tea.": "We confirm that an email address change has been made to your My Own Tea account.",
  "Nous serions heureux de vous revoir chez My Own Tea.": "We would be happy to see you again at My Own Tea.",
  "Nous vous rappelons que vous pouvez renouveler votre sélection.": "We remind you that you can renew your selection.",
  "Nouvel email": "New email",
  "Nouvelles de My Own Tea": "News from My Own Tea",
  "Nouvelles idées pour accompagner votre commande": "New ideas to accompany your order",
  "On serait ravis de vous retrouver": "We would be delighted to see you again",
  "Paiement valide (Stripe success)": "Valid payment (Stripe success)",
  "Paiement validé automatiquement": "Payment validated automatically",
  "Par mesure de sécurité, ne transférez jamais ce lien à un tiers.": "For security reasons, never transfer this link to a third party.",
  "Partagez votre retour sur votre commande en quelques instants.": "Share your feedback on your order in just a few moments.",
  "Produit en rupture de stock": "Product out of stock",
  "Prolongez votre expérience": "Extend your experience",
  "Rafraîchissement manuel du tracking": "Manual tracking refresh",
  "Réassort en quelques clics": "Restock in just a few clicks",
  "Réassort infusion: votre rappel": "Infusion refill: your reminder",
  "Réconciliation paiements": "Payment reconciliation",
  "Réinitialisation de votre mot de passe": "Resetting your password",
  "Réinitialisation de votre mot de passe My Own Tea": "Resetting your My Own Tea password",
  "Réinitialiser mon mot de passe": "Reset my password",
  "Relances de reachat J+21/J+35.": "Repurchase reminders D+21/D+35.",
  "Relances panier a H+1 et H+24 si aucune commande.": "Basket reminders at H+1 and H+24 if no order.",
  "Relancez facilement une nouvelle commande depuis votre espace client.": "Easily reissue a new order from your customer area.",
  "Reprendre mon panier": "Resume my cart",
  "Reprenez votre commande en un clic": "Resume your order in one click",
  "Restez toujours approvisionné": "Always stay stocked",
  "Retrouvez nos dernières nouveautés et idées de dégustation.": "Find our latest news and tasting ideas.",
  "Retrouvez vos favoris ou composez une nouvelle création.": "Find your favorites or compose a new creation.",
  "Retrouvez vos rituels infusion": "Find your infusion rituals",
  "Retrouvez vos saveurs préférées rapidement": "Find your favorite flavors quickly",
  "Revenez découvrir les dernières créations": "Come back and discover the latest creations",
  "Revenez explorer nos nouveautés et inspirations du moment.": "Come back and explore our current news and inspirations.",
  "Revenir sur la boutique": "Return to the store",
  "Si un compte existe avec cet email, un lien de réinitialisation a été envoyé.": "If an account exists with this email, a reset link has been sent.",
  "Si vous avez une question, notre équipe support reste disponible pour vous aider.": "If you have a question, our support team remains available to help you.",
  "Si vous n'êtes pas à l'origine de ce changement, sécurisez immédiatement votre compte.": "If you are not the cause of this change, secure your account immediately.",
  "Si vous n'êtes pas à l'origine de cette action, lancez immédiatement une réinitialisation.": "If you are not the cause of this action, initiate a reset immediately.",
  "Si vous n'êtes pas à l'origine de cette demande, vous pouvez ignorer cet email.": "If you are not the originator of this request, you can ignore this email.",
  "Si vous suspectez un accès non autorisé, contactez rapidement notre support.": "If you suspect unauthorized access, contact our support promptly.",
  "Signale les commandes bloquées trop longtemps en CONFIRMED ou PROCESSING.": "Reports commands blocked for too long in CONFIRMED or PROCESSING.",
  "Stock insuffisant pour un produit": "Insufficient stock for a product",
  "Stock insuffisant pour une variante": "Insufficient stock for a variant",
  "Stripe non configuré, réconciliation ignorée": "Stripe not configured, reconciliation ignored",
  "Suivre mon colis": "Track my package",
  "Synchronisation automatique du tracking transporteur": "Automatic synchronization of carrier tracking",
  "Synchronise le tracking Boxtal et met à jour les statuts SHIPPED/DELIVERED.": "Synchronizes Boxtal tracking and updates SHIPPED/DELIVERED statuses.",
  "Toujours intéressé(e) par My Own Tea ?": "Still interested in My Own Tea?",
  "Tracking et transporteur requis pour passer en SHIPPED": "Tracking and carrier required to upgrade to SHIPPED",
  "Transition de statut non autorisée": "Unauthorized status transition",
  "Un même ingrédient ne peut pas être sélectionné plusieurs fois.": "The same ingredient cannot be selected several times.",
  "Une adresse email destinataire valide est requise": "A valid recipient email address is required",
  "Utilisez le type PACK pour ajouter ce pack.": "Use the PACK type to add this pack.",
  "Utilisez le type SUBSCRIPTION pour ajouter cet abonnement.": "Use the SUBSCRIPTION type to add this subscription.",
  "Vérification du rendu email My Own Tea": "Checking the My Own Tea email rendering",
  "Vérifie les commandes PENDING Stripe et confirme automatiquement les paiements validés.": "Verifies PENDING Stripe orders and automatically confirms validated payments.",
  "Vérifier mon compte": "Verify my account",
  "Veuillez choisir une variante pour ce produit.": "Please choose a variant for this product.",
  "Voir la boutique": "View the store",
  "Voir les inspirations": "See the inspirations",
  "Voir les suggestions": "See suggestions",
  "Voir ma commande": "View my order",
  "Vos infusions préférées sont peut-être bientôt terminées.": "Your favorite infusions may be almost finished.",
  "votre adresse email": "Your email address",
  "Votre adresse email de connexion a été modifiée": "Your login email address has been changed",
  "Votre avis compte pour nous": "Your opinion matters to us",
  "Votre colis a été remis au transporteur. Vous pouvez suivre son acheminement.": "Your package has been delivered to the carrier. You can follow its progress.",
  "Votre commande": "Your order",
  "Votre commande a été annulée. Si besoin, notre équipe peut vous accompagner.": "Your order has been canceled. If necessary, our team can support you.",
  "Votre commande est actuellement en préparation dans notre atelier.": "Your order is currently being prepared in our workshop.",
  "Votre commande est marquée comme livrée. Bonne dégustation !": "Your order is marked as delivered. Happy tasting!",
  "Votre désinscription est prise en compte.": "Your unsubscription is taken into account.",
  "Votre email de compte a été modifié": "Your account email has been changed",
  "Votre feedback est précieux pour faire évoluer My Own Tea.": "Your feedback is valuable in developing My Own Tea.",
  "Votre mot de passe a été modifié": "Your password has been changed",
  "Votre paiement est validé. Nous préparons votre commande avec soin.": "Your payment is validated. We prepare your order with care.",
  "Votre panier est prêt": "Your basket is ready",
  "Votre panier est toujours en attente.": "Your cart is still waiting.",
  "Votre panier vous attend": "Your basket is waiting for you",
  "Votre prochain réassort est prêt": "Your next restock is ready",
  "Votre retour nous aide à améliorer nos créations": "Your feedback helps us improve our creations",
  "Votre sélection est toujours disponible": "Your selection is still available",
  "Vous avez laissé des articles dans votre panier.": "You left items in your cart.",
  "Vous êtes déjà inscrit(e) à la newsletter.": "You are already subscribed to the newsletter.",
  "Vous pouvez consulter le détail de votre commande depuis votre espace client.": "You can view the details of your order from your customer area.",
  "Vous pouvez partir sur une base douce et ajouter 2 à 3 ingrédients complémentaires.": "You can start with a mild base and add 2 to 3 complementary ingredients.",
  "Vous recevez cet email car vous êtes inscrit(e) à nos communications.": "You are receiving this email because you are subscribed to our communications.",
  "Adresse destinataire": "Recipient address",
  "Code non appliqué: ce code a atteint sa limite par client.": "Code not applied: This code has reached its limit per customer.",
  "Code non appliqué: ce code a atteint sa limite totale d'utilisations.": "Code not applied: this code has reached its total usage limit.",
  "Code non appliqué: ce code est hors période de validité.": "Code not applied: this code is out of validity.",
  "Code non appliqué: ce code est inactif.": "Code not applied: This code is inactive.",
  "Code non appliqué: ce code est invalide.": "Code not applied: This code is invalid.",
  "Code non appliqué: ce code est moins avantageux qu'une remise déjà active.": "Code not applied: this code is less advantageous than an already active discount.",
  "Code non appliqué: ce code n'est pas éligible actuellement.": "Code not applied: This code is not currently eligible.",
  "Code non appliqué: cette remise est réservée à la première commande (vous avez déjà une commande payée/confirmée avec ce code).": "Code not applied: this discount is reserved for the first order (you already have a paid/confirmed order with this code).",
  "Code non appliqué: connectez-vous pour utiliser ce code.": "Code not applied: Log in to use this code.",
  "Email already registered": "Email already registered",
  "Ingrédient supprimé": "Ingredient removed",
  "Adresse expéditeur": "Sender address",
  "Ingrédient de test": "Test ingredient"
}
